README.md
setup.py
imm_webform.egg-info/PKG-INFO
imm_webform.egg-info/SOURCES.txt
imm_webform.egg-info/dependency_links.txt
imm_webform.egg-info/entry_points.txt
imm_webform.egg-info/requires.txt
imm_webform.egg-info/top_level.txt
webform/__init__.py
webform/prdata.py
webform/bcpnp/__init__.py
webform/bcpnp/dashboard.py
webform/bcpnp/data.py
webform/bcpnp/education.py
webform/bcpnp/employment.py
webform/bcpnp/login.py
webform/bcpnp/register.py
webform/bcpnp/registrant.py
webform/models/__init__.py
webform/models/bcpnpmodel.py
webform/models/definition.py
webform/models/element.py
webform/models/engine.py
webform/models/pr/__init__ copy.py
webform/models/pr/__init__.py
webform/models/pr/prmodel.py
webform/prportal/__init__.py
webform/prportal/application.py
webform/prportal/i0008.py
webform/prportal/i5406.py
webform/prportal/i5562.py
webform/prportal/i5669.py
webform/prportal/login.py
webform/prportal/data/__init__.py
webform/prportal/data/citizen.py
webform/prportal/data/country_birth.py
webform/prportal/data/country_residence.py
webform/prportal/data/d0008.py