Metadata-Version: 2.1
Name: imm-webform
Version: 1.2.1
Summary: A python client library used to describe program model and get validated data.
Home-page: UNKNOWN
Author: Jacky Zhang
Author-email: jackyzhang1969@gmail.com
License: UNKNOWN
Keywords: Canada,Immigration,Case,Programs,APIs,web,form,programtically filling
Platform: UNKNOWN
Classifier: Development Status :: 3 - Alpha
Classifier: Intended Audience :: Developers
Classifier: Intended Audience :: Science/Research
Classifier: Intended Audience :: Financial and Insurance Industry
Classifier: License :: OSI Approved :: MIT License
Classifier: Natural Language :: English
Classifier: Operating System :: OS Independent
Classifier: Programming Language :: Python
Classifier: Programming Language :: Python :: 3
Classifier: Programming Language :: Python :: 3.10
Requires-Python: >=3.10
